[
  {
    "original": "Meeting will be at 8 a.m.",
    "translated": "Зустріч відбудеться о 8 ранку"
  },
  {
    "original": "Can we have a meeting next week?",
    "translated": "Ми можемо зустрітися наступного тижня?"
  },
  {
    "original": "Our team will sign the contract with the client",
    "translated": "Наша команда підпише контракт з клієнтом"
  },
  {
    "original": "Please, leave a message",
    "translated": "Будь ласка, залиште повідомлення"
  },
  {
    "original": "Round-trip flight",
    "translated": "Політ в обидва кінці"
  },
  {
    "original": "Business card",
    "translated": "Бізнес карта"
  },
  {
    "original": "Full-time job",
    "translated": "Робота на повний робочий день"
  },
  {
    "original": "Part-time job",
    "translated": "Робота за сумісництвом"
  },
  {
    "original": "Internship",
    "translated": "Стажування"
  },
  {
    "original": "Accounting",
    "translated": "Бухгалтерський облік"
  },
  {
    "original": "Consulting",
    "translated": "Консалтинг"
  },
  {
    "original": "Market",
    "translated": "Ринок"
  },
  {
    "original": "Insurance",
    "translated": "Страхування"
  },
  {
    "original": "Stock exchange",
    "translated": "Фондова біржа"
  },
  {
    "original": "Bankruptcy",
    "translated": "Банкрутство"
  },
  {
    "original": "Demand",
    "translated": "Попит"
  },
  {
    "original": "Supply",
    "translated": "Постачання"
  },
  {
    "original": "Income",
    "translated": "Дохід"
  },
  {
    "original": "Interest",
    "translated": "Інтерес"
  },
  {
    "original": "Invoice",
    "translated": "Рахунок-фактура"
  },
  {
    "original": "Tax",
    "translated": "Податок"
  },
  {
    "original": "Share",
    "translated": "Участь"
  },
  {
    "original": "Shareholder",
    "translated": "Акціонер"
  },
  {
    "original": "Union",
    "translated": "Союз"
  }
]